celltypetree/__init__.py
celltypetree/aggregation.py
celltypetree/annotation.py
celltypetree/harmonization.py
celltypetree/tree.py
celltypetree-0.1.18.dist-info/licenses/LICENSE
celltypetree-0.1.18.dist-info/METADATA
celltypetree-0.1.18.dist-info/WHEEL
celltypetree-0.1.18.dist-info/top_level.txt
celltypetree-0.1.18.dist-info/RECORD
