Metadata-Version: 2.4
Name: celltypetree
Version: 0.1.18
Summary: Single-Cell RNA-Seq label harmonization and aggregation on a tree of cell types
Author: Lorenzo Amir Nemati Fard
License: MIT
Project-URL: Homepage, https://github.com/lorenzoamir/celltypetree
License-File: LICENSE
Requires-Dist: numpy
Requires-Dist: pandas
Requires-Dist: networkx
Requires-Dist: anndata
Requires-Dist: scanpy
Provides-Extra: decoupler
Requires-Dist: decoupler; extra == "decoupler"
Requires-Dist: omnipath; extra == "decoupler"
Requires-Dist: igraph; extra == "decoupler"
Provides-Extra: celltypist
Requires-Dist: celltypist; extra == "celltypist"
Provides-Extra: cellhint
Requires-Dist: cellhint; extra == "cellhint"
Provides-Extra: crowdkit
Requires-Dist: crowd-kit; extra == "crowdkit"
Provides-Extra: crowd-kit
Requires-Dist: crowd-kit; extra == "crowd-kit"
Provides-Extra: all
Requires-Dist: decoupler; extra == "all"
Requires-Dist: omnipath; extra == "all"
Requires-Dist: igraph; extra == "all"
Requires-Dist: celltypist; extra == "all"
Requires-Dist: cellhint; extra == "all"
Requires-Dist: crowd-kit; extra == "all"
Dynamic: license-file
